lazystuff/__init__.py
lazystuff/lazydict.py
lazystuff/lazylist.py
lazystuff/py.typed
lazystuff-1.2.0.dist-info/LICENSE
lazystuff-1.2.0.dist-info/METADATA
lazystuff-1.2.0.dist-info/WHEEL
lazystuff-1.2.0.dist-info/top_level.txt
lazystuff-1.2.0.dist-info/RECORD
