Metadata-Version: 2.1
Name: lazystuff
Version: 1.2.0
Summary: Lazy-ish list-like objects for streaming APIs.
Author-email: David Byers <david.byers@liu.se>
License: AGPL-3.0-or-later
Project-URL: Homepage, https://github.com/ookisan/lazystuff
Project-URL: Issues, https://github.com/ookisan/lazystuff/issues
Keywords: lazy,sequence
Classifier: Development Status :: 5 - Production/Stable
Classifier: Intended Audience :: Developers
Classifier: License :: OSI Approved :: GNU Affero General Public License v3 or later (AGPLv3+)
Classifier: Topic :: Software Development :: Libraries :: Python Modules
Classifier: Programming Language :: Python
Classifier: Typing :: Typed
Requires-Python: >=3.9
License-File: LICENSE
Provides-Extra: dev
Requires-Dist: Flake8-pyproject ; extra == 'dev'
Requires-Dist: build ; extra == 'dev'
Requires-Dist: flake8 ; extra == 'dev'
Requires-Dist: mypy ; extra == 'dev'
Requires-Dist: pydocstyle ; extra == 'dev'
Requires-Dist: pylint ; extra == 'dev'
Requires-Dist: pytest ; extra == 'dev'
Requires-Dist: pytest-cov ; extra == 'dev'
Requires-Dist: sphinx ; extra == 'dev'
Requires-Dist: sphinx-markdown-builder ; extra == 'dev'
Requires-Dist: sphinx-rtd-theme ; extra == 'dev'
Requires-Dist: twine ; extra == 'dev'
Requires-Dist: vulture ; extra == 'dev'
Requires-Dist: wheel ; extra == 'dev'
